apache_beam/google_version.py
apache_beam/__init__.py
apache_beam/pvalue.py
apache_beam/error.py
apache_beam/dataflow_test.py
apache_beam/version.py
apache_beam/pvalue_test.py
apache_beam/pipeline.py
apache_beam/pipeline_test.py
apache_beam/internal/module_test.py
apache_beam/internal/windmill_service_pb2.py
apache_beam/internal/pickler_test.py
apache_beam/internal/__init__.py
apache_beam/internal/util_test.py
apache_beam/internal/auth.py
apache_beam/internal/apiclient_test.py
apache_beam/internal/json_value.py
apache_beam/internal/json_value_test.py
apache_beam/internal/pickler.py
apache_beam/internal/util.py
apache_beam/internal/apiclient.py
apache_beam/internal/windmill_pb2.py
apache_beam/internal/clients/__init__.py
apache_beam/internal/clients/bigquery/__init__.py
apache_beam/internal/clients/bigquery/bigquery_v2_client.py
apache_beam/internal/clients/bigquery/bigquery_v2_messages.py
apache_beam/internal/clients/storage/__init__.py
apache_beam/internal/clients/storage/storage_v1_messages.py
apache_beam/internal/clients/storage/storage_v1_client.py
apache_beam/internal/clients/dataflow/__init__.py
apache_beam/internal/clients/dataflow/dataflow_v1b3_client.py
apache_beam/internal/clients/dataflow/dataflow_v1b3_messages.py
apache_beam/utils/counters.pxd
apache_beam/utils/names.py
apache_beam/utils/retry_test.py
apache_beam/utils/__init__.py
apache_beam/utils/processes.py
apache_beam/utils/counters.py
apache_beam/utils/dependency.py
apache_beam/utils/windowed_value.pxd
apache_beam/utils/profiler.py
apache_beam/utils/path_test.py
apache_beam/utils/pipeline_options_test.py
apache_beam/utils/windowed_value_test.py
apache_beam/utils/dependency_test.py
apache_beam/utils/windowed_value.py
apache_beam/utils/options.py
apache_beam/utils/processes_test.py
apache_beam/utils/retry.py
apache_beam/utils/pipeline_options_validator_test.py
apache_beam/utils/pipeline_options_validator.py
apache_beam/utils/path.py
google_cloud_dataflow-0.4.0rc2.dist-info/metadata.json
google_cloud_dataflow-0.4.0rc2.dist-info/METADATA
google_cloud_dataflow-0.4.0rc2.dist-info/DESCRIPTION.rst
google_cloud_dataflow-0.4.0rc2.dist-info/top_level.txt
google_cloud_dataflow-0.4.0rc2.dist-info/RECORD
google_cloud_dataflow-0.4.0rc2.dist-info/WHEEL
